kleinberg_grid_simulator/__init__.py
kleinberg_grid_simulator/julia_implementation/__init__.py
kleinberg_grid_simulator/julia_implementation/julia_edt.py
kleinberg_grid_simulator/julia_implementation/kleingrid.jl
kleinberg_grid_simulator/juliapkg.json
kleinberg_grid_simulator/kleingrid.py
kleinberg_grid_simulator/python_implementation/__init__.py
kleinberg_grid_simulator/python_implementation/greedy_walk.py
kleinberg_grid_simulator/python_implementation/python_edt.py
kleinberg_grid_simulator/python_implementation/seed.py
kleinberg_grid_simulator/python_implementation/shortcuts.py
kleinberg_grid_simulator/utils.py
kleinberg_grid_simulator-0.1.0.dist-info/LICENSE
kleinberg_grid_simulator-0.1.0.dist-info/METADATA
kleinberg_grid_simulator-0.1.0.dist-info/WHEEL
kleinberg_grid_simulator-0.1.0.dist-info/RECORD
