Metadata-Version: 2.1
Name: kleinberg-grid-simulator
Version: 0.1.0
Summary: A Python+Julia package to compute Expected Delivery Time in Kleinberg's augmented grid model.
Home-page: https://github.com/balouf/kleinberg-grid-simulator
Author: Fabien Mathieu
Author-email: loufab@gmail.com
Requires-Python: >=3.9,<3.12
Classifier: Programming Language :: Python :: 3
Classifier: Programming Language :: Python :: 3.9
Classifier: Programming Language :: Python :: 3.10
Classifier: Programming Language :: Python :: 3.11
Requires-Dist: joblib (>=1.3.2,<2.0.0)
Requires-Dist: juliacall (>=0.9.15,<0.10.0)
Requires-Dist: numba (>=0.58.1,<0.59.0)
Requires-Dist: tqdm (>=4.66.1,<5.0.0)
Requires-Dist: types-tqdm (>=4.66.0.5,<5.0.0.0)
Project-URL: Documentation, https://balouf.github.io/kleinberg-grid-simulator
Project-URL: Repository, https://github.com/balouf/kleinberg-grid-simulator
